autharmor_sdk/__init__.py
autharmor_sdk/autharmor_sdk.py
autharmor_sdk/config.py
autharmor_sdk-0.1.5.dist-info/LICENSE
autharmor_sdk-0.1.5.dist-info/METADATA
autharmor_sdk-0.1.5.dist-info/WHEEL
autharmor_sdk-0.1.5.dist-info/top_level.txt
autharmor_sdk-0.1.5.dist-info/RECORD
