Metadata-Version: 2.1
Name: autharmor-sdk
Version: 0.1.5
Summary: Auth Armor SDK for Python
Home-page: https://github.com/autharmor/autharmor-sdk-py
Author: Auth Armor
Author-email: support@autharmor.com
Project-URL: Documentation, https://github.com/autharmor/autharmor-sdk-py
Project-URL: Bug Reports, https://github.com/autharmor/autharmor-sdk-py/issues
Project-URL: Source Code, https://github.com/autharmor/autharmor-sdk-py
Keywords: example,pypi,package
Classifier: Development Status :: 5 - Production/Stable
Classifier: Intended Audience :: Developers
Classifier: Topic :: Software Development :: Build Tools
Classifier: Programming Language :: Python :: 3
Classifier: Programming Language :: Python :: 3.6
Classifier: Programming Language :: Python :: 3.7
Classifier: Programming Language :: Python :: 3.8
Classifier: Programming Language :: Python :: 3.9
Classifier: Programming Language :: Python :: 3.10
Classifier: Programming Language :: Python :: 3 :: Only
Classifier: License :: OSI Approved :: MIT License
Classifier: Operating System :: OS Independent
Requires-Python: >=3.6
License-File: LICENSE
Requires-Dist: requests
Provides-Extra: dev
Requires-Dist: check-manifest ; extra == 'dev'
